[
  {
    "date": "2026-02-22T18:00:00Z",
    "hauteur": 0.323,
    "debit": 0.219,
    "rain_mm": 0.0
  },
  {
    "date": "2026-02-22T18:00:00Z",
    "hauteur": 0.323,
    "debit": 0.219,
    "rain_mm": 0.0
  },
  {
    "date": "2026-02-22T18:00:00Z",
    "hauteur": 0.323,
    "debit": 0.219,
    "rain_mm": 0.0
  },
  {
    "date": "2026-02-22T18:00:00Z",
    "hauteur": 0.323,
    "debit": 0.219,
    "rain_mm": 0.0
  },
  {
    "date": "2026-02-22T18:00:00Z",
    "hauteur": 0.323,
    "debit": 0.219,
    "rain_mm": 0.2
  },
  {
    "date": "2026-02-22T18:00:00Z",
    "hauteur": 0.323,
    "debit": 0.219,
    "rain_mm": 0.4
  },
  {
    "date": "2026-02-22T20:00:00Z",
    "hauteur": 0.34,
    "debit": 0.246,
    "rain_mm": 0.2
  },
  {
    "date": "2026-02-22T20:00:00Z",
    "hauteur": 0.34,
    "debit": 0.246,
    "rain_mm": 0.2
  },
  {
    "date": "2026-02-22T20:00:00Z",
    "hauteur": 0.34,
    "debit": 0.246,
    "rain_mm": 0.1
  },
  {
    "date": "2026-02-22T20:00:00Z",
    "hauteur": 0.34,
    "debit": 0.246,
    "rain_mm": 0.1
  },
  {
    "date": "2026-02-22T20:00:00Z",
    "hauteur": 0.34,
    "debit": 0.246,
    "rain_mm": 0.1
  },
  {
    "date": "2026-02-22T20:00:00Z",
    "hauteur": 0.34,
    "debit": 0.246,
    "rain_mm": 0.0
  },
  {
    "date": "2026-02-22T20:00:00Z",
    "hauteur": 0.34,
    "debit": 0.246,
    "rain_mm": 0.0
  },
  {
    "date": "2026-02-22T20:00:00Z",
    "hauteur": 0.34,
    "debit": 0.246,
    "rain_mm": 0.0
  },
  {
    "date": "2026-02-22T20:00:00Z",
    "hauteur": 0.34,
    "debit": 0.246,
    "rain_mm": 0.0
  },
  {
    "date": "2026-02-22T20:00:00Z",
    "hauteur": 0.34,
    "debit": 0.246,
    "rain_mm": 0.0
  },
  {
    "date": "2026-02-22T20:00:00Z",
    "hauteur": 0.34,
    "debit": 0.246,
    "rain_mm": 0.0
  },
  {
    "date": "2026-02-22T20:00:00Z",
    "hauteur": 0.34,
    "debit": 0.246,
    "rain_mm": 0.0
  },
  {
    "date": "2026-02-22T20:00:00Z",
    "hauteur": 0.34,
    "debit": 0.246,
    "rain_mm": 0.0
  },
  {
    "date": "2026-02-23T10:00:00Z",
    "hauteur": 0.284,
    "debit": 0.161,
    "rain_mm": 0.0
  },
  {
    "date": "2026-02-23T12:00:00Z",
    "hauteur": 0.288,
    "debit": 0.167,
    "rain_mm": 0.0
  },
  {
    "date": "2026-02-24T10:00:00Z",
    "hauteur": 0.257,
    "debit": 0.123,
    "rain_mm": 0.0
  },
  {
    "date": "2026-02-24T12:00:00Z",
    "hauteur": 0.263,
    "debit": 0.131,
    "rain_mm": 0.0
  },
  {
    "date": "2026-02-25T10:00:00Z",
    "hauteur": 0.244,
    "debit": 0.105,
    "rain_mm": 0.0
  },
  {
    "date": "2026-02-25T12:00:00Z",
    "hauteur": 0.244,
    "debit": 0.105,
    "rain_mm": 0.0
  }
]